<?xml version="1.0" encoding="UTF-8"?>
<flores><articulo><nombre>Rosa</nombre><precio>3.00</precio><color>Rojo</color><cantidad>2000</cantidad><iva>20.00</iva><foto>http://partyflowers.com/mvc/img/RosaRoja.jpeg</foto></articulo><articulo><nombre>Paniculata</nombre><precio>3.00</precio><color>Blanco</color><cantidad>1000</cantidad><iva>20.00</iva><foto>http://partyflowers.com/mvc/img/paniculata.jpg</foto></articulo><articulo><nombre>Clavel</nombre><precio>0.50</precio><color>Lila</color><cantidad>2500</cantidad><iva>20.00</iva><foto>http://partyflowers.com/mvc/img/Clavel.jpg</foto></articulo><articulo><nombre>Gladiolo</nombre><precio>1.00</precio><color>Blanco</color><cantidad>200</cantidad><iva>20.00</iva><foto>http://partyflowers.com/mvc/img/gladiolo.jpg</foto></articulo><articulo><nombre>Lilium</nombre><precio>2.00</precio><color>Lila</color><cantidad>50</cantidad><iva>20.00</iva><foto>http://partyflowers.com/mvc/img/lilium.jpg</foto></articulo><articulo><nombre>Helecho</nombre><precio>0.45</precio><color>Verde</color><cantidad>430</cantidad><iva>20.00</iva><foto>http://partyflowers.com/mvc/img/helecho.jpg</foto></articulo><articulo><nombre>Cactus</nombre><precio>6.00</precio><color>Verde</color><cantidad>10</cantidad><iva>20.00</iva><foto>http://partyflowers.com/mvc/img/cactus.jpg</foto></articulo><articulo><nombre>Cactus con flores</nombre><precio>8.00</precio><color>Verde</color><cantidad>5</cantidad><iva>20.00</iva><foto>http://partyflowers.com/mvc/img/cactusflor.jpeg</foto></articulo></flores>
